README.md
scrapysplashwrapper/__init__.py
scrapysplashwrapper/crawl.lua
scrapysplashwrapper/crawler.py
scrapysplashwrapper/exceptions.py
scrapysplashwrapper/middleware.py
scrapysplashwrapper/py.typed
scrapysplashwrapper-1.11.0.dist-info/entry_points.txt
scrapysplashwrapper-1.11.0.dist-info/LICENSE
scrapysplashwrapper-1.11.0.dist-info/WHEEL
scrapysplashwrapper-1.11.0.dist-info/METADATA
scrapysplashwrapper-1.11.0.dist-info/RECORD
