Metadata-Version: 2.1
Name: scrapysplashwrapper
Version: 1.11.0
Summary: Scrapy splash wrapper as a standalone library.
Home-page: https://github.com/Lookyloo/ScrapySplashWrapper
License: BSD-3-Clause
Author: Raphaël Vinot
Author-email: raphael.vinot@circl.lu
Requires-Python: >=3.8,<4.0
Classifier: Environment :: Console
Classifier: Intended Audience :: Science/Research
Classifier: Intended Audience :: Telecommunications Industry
Classifier: License :: OSI Approved :: BSD License
Classifier: Programming Language :: Python :: 3
Classifier: Programming Language :: Python :: 3.10
Classifier: Programming Language :: Python :: 3.8
Classifier: Programming Language :: Python :: 3.9
Classifier: Topic :: Internet
Classifier: Topic :: Security
Provides-Extra: docs
Requires-Dist: Scrapy (>=2.6.1,<3.0.0)
Requires-Dist: Sphinx (>=4.5.0,<5.0.0); extra == "docs"
Requires-Dist: lxml (>=4.8.0,<5.0.0)
Requires-Dist: scrapy-splash (>=0.8.0,<0.9.0)
Project-URL: Documentation, https://scrapysplashwrapper.readthedocs.io/en/latest/
Project-URL: Repository, https://github.com/Lookyloo/ScrapySplashWrapper
